{
  "kanji": "三",
  "unicode": "4E09",
  "stroke_count": 3,
  "strokes": [
    {
      "points": [
        {
          "x": 68,
          "y": 96
        },
        {
          "x": 80,
          "y": 102
        },
        {
          "x": 220,
          "y": 97
        }
      ],
      "path": "M 68,96 L 80,102 L 220,97",
      "taper": false
    },
    {
      "points": [
        {
          "x": 85,
          "y": 162
        },
        {
          "x": 198,
          "y": 156
        },
        {
          "x": 208,
          "y": 165
        }
      ],
      "path": "M 85,162 L 198,156 L 208,165",
      "taper": false
    },
    {
      "points": [
        {
          "x": 48,
          "y": 242
        },
        {
          "x": 252,
          "y": 242
        }
      ],
      "path": "M 48,242 L 252,242",
      "taper": false
    }
  ]
}