{
  "kanji": "六",
  "unicode": "516D",
  "stroke_count": 4,
  "strokes": [
    {
      "points": [
        {
          "x": 138,
          "y": 67
        },
        {
          "x": 150,
          "y": 79
        },
        {
          "x": 151,
          "y": 101
        },
        {
          "x": 147,
          "y": 106
        }
      ],
      "path": "M 138,67 L 150,79 L 151,101 L 147,106",
      "taper": false
    },
    {
      "points": [
        {
          "x": 43,
          "y": 132
        },
        {
          "x": 120,
          "y": 130
        },
        {
          "x": 156,
          "y": 110
        },
        {
          "x": 193,
          "y": 126
        },
        {
          "x": 246,
          "y": 123
        }
      ],
      "path": "M 43,132 L 120,130 L 156,110 L 193,126 L 246,123",
      "taper": false
    },
    {
      "points": [
        {
          "x": 111,
          "y": 182
        },
        {
          "x": 54,
          "y": 259
        }
      ],
      "path": "M 111,182 L 54,259",
      "taper": true
    },
    {
      "points": [
        {
          "x": 187,
          "y": 190
        },
        {
          "x": 194,
          "y": 188
        },
        {
          "x": 236,
          "y": 232
        },
        {
          "x": 242,
          "y": 241
        },
        {
          "x": 237,
          "y": 249
        }
      ],
      "path": "M 187,190 L 194,188 L 236,232 L 242,241 L 237,249",
      "taper": false
    }
  ]
}