{
  "kanji": "気",
  "unicode": "6C17",
  "stroke_count": 6,
  "strokes": [
    {
      "points": [
        {
          "x": 106,
          "y": 68
        },
        {
          "x": 95,
          "y": 94
        }
      ],
      "path": "M 106,68 L 95,94",
      "taper": true
    },
    {
      "points": [
        {
          "x": 106,
          "y": 68
        },
        {
          "x": 101,
          "y": 83
        },
        {
          "x": 103,
          "y": 93
        },
        {
          "x": 235,
          "y": 88
        }
      ],
      "path": "M 106,68 L 101,83 L 103,93 L 235,88",
      "taper": false
    },
    {
      "points": [
        {
          "x": 95,
          "y": 94
        },
        {
          "x": 103,
          "y": 78
        },
        {
          "x": 103,
          "y": 93
        },
        {
          "x": 235,
          "y": 88
        }
      ],
      "path": "M 95,94 L 103,78 L 103,93 L 235,88",
      "taper": false
    },
    {
      "points": [
        {
          "x": 59,
          "y": 136
        },
        {
          "x": 69,
          "y": 145
        },
        {
          "x": 169,
          "y": 139
        },
        {
          "x": 183,
          "y": 145
        },
        {
          "x": 205,
          "y": 144
        },
        {
          "x": 214,
          "y": 225
        },
        {
          "x": 230,
          "y": 249
        },
        {
          "x": 251,
          "y": 269
        },
        {
          "x": 255,
          "y": 269
        },
        {
          "x": 261,
          "y": 249
        }
      ],
      "path": "M 59,136 L 69,145 L 169,139 L 183,145 L 205,144 L 214,225 L 230,249 L 251,269 L 255,269 L 261,249",
      "taper": false
    },
    {
      "points": [
        {
          "x": 158,
          "y": 148
        },
        {
          "x": 160,
          "y": 178
        },
        {
          "x": 151,
          "y": 193
        },
        {
          "x": 130,
          "y": 216
        },
        {
          "x": 125,
          "y": 216
        },
        {
          "x": 123,
          "y": 224
        },
        {
          "x": 76,
          "y": 262
        }
      ],
      "path": "M 158,148 L 160,178 L 151,193 L 130,216 L 125,216 L 123,224 L 76,262",
      "taper": true
    },
    {
      "points": [
        {
          "x": 82,
          "y": 186
        },
        {
          "x": 171,
          "y": 255
        }
      ],
      "path": "M 82,186 L 171,255",
      "taper": false
    }
  ]
}