{
  "kanji": "石",
  "unicode": "77F3",
  "stroke_count": 5,
  "strokes": [
    {
      "points": [
        {
          "x": 55,
          "y": 91
        },
        {
          "x": 247,
          "y": 91
        }
      ],
      "path": "M 55,91 L 247,91",
      "taper": false
    },
    {
      "points": [
        {
          "x": 117,
          "y": 93
        },
        {
          "x": 125,
          "y": 119
        },
        {
          "x": 43,
          "y": 217
        }
      ],
      "path": "M 117,93 L 125,119 L 43,217",
      "taper": true
    },
    {
      "points": [
        {
          "x": 104,
          "y": 174
        },
        {
          "x": 104,
          "y": 255
        }
      ],
      "path": "M 104,174 L 104,255",
      "taper": false
    },
    {
      "points": [
        {
          "x": 107,
          "y": 158
        },
        {
          "x": 205,
          "y": 159
        },
        {
          "x": 205,
          "y": 220
        }
      ],
      "path": "M 107,158 L 205,159 L 205,220",
      "taper": false
    },
    {
      "points": [
        {
          "x": 112,
          "y": 250
        },
        {
          "x": 218,
          "y": 250
        }
      ],
      "path": "M 112,250 L 218,250",
      "taper": false
    }
  ]
}