{
  "kanji": "足",
  "unicode": "8DB3",
  "stroke_count": 7,
  "strokes": [
    {
      "points": [
        {
          "x": 88,
          "y": 75
        },
        {
          "x": 99,
          "y": 118
        }
      ],
      "path": "M 88,75 L 99,118",
      "taper": false
    },
    {
      "points": [
        {
          "x": 88,
          "y": 74
        },
        {
          "x": 204,
          "y": 74
        },
        {
          "x": 204,
          "y": 98
        }
      ],
      "path": "M 88,74 L 204,74 L 204,98",
      "taper": false
    },
    {
      "points": [
        {
          "x": 101,
          "y": 106
        },
        {
          "x": 203,
          "y": 106
        }
      ],
      "path": "M 101,106 L 203,106",
      "taper": false
    },
    {
      "points": [
        {
          "x": 151,
          "y": 138
        },
        {
          "x": 151,
          "y": 239
        }
      ],
      "path": "M 151,138 L 151,239",
      "taper": false
    },
    {
      "points": [
        {
          "x": 152,
          "y": 163
        },
        {
          "x": 166,
          "y": 142
        },
        {
          "x": 206,
          "y": 138
        }
      ],
      "path": "M 152,163 L 166,142 L 206,138",
      "taper": false
    },
    {
      "points": [
        {
          "x": 102,
          "y": 148
        },
        {
          "x": 92,
          "y": 196
        },
        {
          "x": 57,
          "y": 252
        }
      ],
      "path": "M 102,148 L 92,196 L 57,252",
      "taper": true
    },
    {
      "points": [
        {
          "x": 94,
          "y": 196
        },
        {
          "x": 104,
          "y": 216
        },
        {
          "x": 148,
          "y": 217
        },
        {
          "x": 176,
          "y": 247
        },
        {
          "x": 253,
          "y": 262
        }
      ],
      "path": "M 94,196 L 104,216 L 148,217 L 176,247 L 253,262",
      "taper": true
    }
  ]
}